<?xml version="1.0" encoding="UTF-8" standalone="no"?>
<menu-config xmlns="http://schemas.haulmont.com/cuba/menu.xsd">
    <menu id="application-stronghold"
          insertBefore="administration">
        <item screen="stronghold$Student.browse"/>
        <item screen="stronghold$Subject.browse"/>
        <item screen="stronghold$Material.browse"/>
        <item screen="stronghold$Course.browse"/>
    </menu>
    <menu id="Directory"
          insertBefore="administration">
        <item screen="stronghold$PositionDirectory.browse"/>
        <item screen="stronghold$ProjectDirectory.browse"/>
        <item screen="stronghold$OrganizationDirectory.browse"/>
        <item screen="stronghold$MaterialsMap.browse"/>
    </menu>
</menu-config>
